AUTHORS.rst
CONTRIBUTING.rst
HISTORY.rst
LICENSE
MANIFEST.in
README.rst
setup.cfg
setup.py
docs/Makefile
docs/authors.rst
docs/conf.py
docs/contributing.rst
docs/history.rst
docs/index.rst
docs/installation.rst
docs/make.bat
docs/readme.rst
docs/usage.rst
rlist_files/__init__.py
rlist_files/list_files.py
rlist_files.egg-info/PKG-INFO
rlist_files.egg-info/SOURCES.txt
rlist_files.egg-info/dependency_links.txt
rlist_files.egg-info/not-zip-safe
rlist_files.egg-info/top_level.txt
tests/__init__.py
tests/test_list_files.py