Metadata-Version: 2.1
Name: rlist-files
Version: 0.0.3
Summary: Function to list the files in directory with pattern recognition and regular expression support.
Home-page: https://github.com/matiasandina/rlist_files
Author: Matias Andina
Author-email: matiasandina@gmail.com
License: MIT license
Keywords: list_files
Platform: UNKNOWN
Classifier: Development Status :: 2 - Pre-Alpha
Classifier: Intended Audience :: Developers
Classifier: License :: OSI Approved :: MIT License
Classifier: Natural Language :: English
Classifier: Programming Language :: Python :: 3
Classifier: Programming Language :: Python :: 3.6
Classifier: Programming Language :: Python :: 3.7
Classifier: Programming Language :: Python :: 3.8
Requires-Python: >=3.6
License-File: LICENSE
License-File: AUTHORS.rst
